m2r2.py
m2r2-0.3.3.post2.dist-info/LICENSE
m2r2-0.3.3.post2.dist-info/METADATA
m2r2-0.3.3.post2.dist-info/WHEEL
m2r2-0.3.3.post2.dist-info/entry_points.txt
m2r2-0.3.3.post2.dist-info/top_level.txt
m2r2-0.3.3.post2.dist-info/RECORD
