Metadata-Version: 2.1
Name: m2r2
Version: 0.3.3.post2
Summary: Markdown and reStructuredText in a single file.
Home-page: https://github.com/crossnox/m2r2
Author: Hiroyuki Takagi
Author-email: miyako.dev@gmail.com
Maintainer: CrossNox
Maintainer-email: ijmermet+m2r2@gmail.com
License: MIT
Keywords: Markdown reStructuredText sphinx-extension
Platform: UNKNOWN
Classifier: Development Status :: 4 - Beta
Classifier: Framework :: Sphinx :: Extension
Classifier: Intended Audience :: Developers
Classifier: License :: OSI Approved :: MIT License
Classifier: Natural Language :: English
Classifier: Programming Language :: Python :: 3
Classifier: Programming Language :: Python :: 3.7
Classifier: Programming Language :: Python :: 3.8
Classifier: Programming Language :: Python :: 3.9
Classifier: Programming Language :: Python :: 3.10
Classifier: Topic :: Text Processing
Requires-Python: >=3.7
